trainify/Trainify.py
trainify/__init__.py
trainify/BBReach/ReachEnv.py
trainify/BBReach/__init__.py
trainify/BBReach/draw.py
trainify/abstract/__init__.py
trainify/abstract/divide_tool.py
trainify/agent/__init__.py
trainify/agent/ddpg_agent.py
trainify/agent/dqn_agent.py
trainify/data/__init__.py
trainify/data/backend_logger_handler.py
trainify/data/logger.py
trainify/data/recorder.py
trainify/data/tensorboard.py
trainify/env/__init__.py
trainify/env/cartpole.py
trainify/env/pendulum.py
trainify/env/BBReach/__init__.py
trainify/env/BBReach/b1.py
trainify/env/BBReach/b4.py
trainify/env/verify/__init__.py
trainify/env/verify/pendulum_env.py
trainify/utils/__init__.py
trainify/utils/backend.py
trainify/utils/class.py
trainify/utils/format.py
trainify/utils/str_list.py
trainify/validator/FMValidator.py
trainify/validator/__init__.py
trainify/validator/cegar.py
trainify/validator/pendulum/__init__.py
trainify/validator/pendulum/pendulum_Relu_3_128_p3.py
trainify/validator/pyModelChecking/__init__.py
trainify/validator/pyModelChecking/graph.py
trainify/validator/pyModelChecking/kripke.py
trainify/validator/pyModelChecking/language.py
trainify/validator/pyModelChecking/parser.py
trainify/validator/pyModelChecking/BDD/BDD.py
trainify/validator/pyModelChecking/BDD/OBDD.py
trainify/validator/pyModelChecking/BDD/__init__.py
trainify/validator/pyModelChecking/BDD/ordering.py
trainify/validator/pyModelChecking/CTL/__init__.py
trainify/validator/pyModelChecking/CTL/language.py
trainify/validator/pyModelChecking/CTL/model_checking.py
trainify/validator/pyModelChecking/CTL/parser.py
trainify/validator/pyModelChecking/CTLS/__init__.py
trainify/validator/pyModelChecking/CTLS/language.py
trainify/validator/pyModelChecking/CTLS/model_checking.py
trainify/validator/pyModelChecking/CTLS/parser.py
trainify/validator/pyModelChecking/LTL/__init__.py
trainify/validator/pyModelChecking/LTL/language.py
trainify/validator/pyModelChecking/LTL/model_checking.py
Trainify_proto-0.2.0.dist-info/METADATA
Trainify_proto-0.2.0.dist-info/WHEEL
Trainify_proto-0.2.0.dist-info/top_level.txt
Trainify_proto-0.2.0.dist-info/RECORD
