Metadata-Version: 2.1
Name: Trainify-proto
Version: 0.2.0
Summary: Trainify-proto
Home-page: https://github.com/jieye-ericx/Trainify-proto
Author: ericx
Author-email: ericxlee@formail.com
Classifier: Programming Language :: Python :: 3
Classifier: License :: OSI Approved :: MIT License
Classifier: Operating System :: OS Independent
Requires-Python: >=3.8
Requires-Dist: torch
Requires-Dist: numpy
Requires-Dist: scipy
Requires-Dist: gym
Requires-Dist: colorlog
Requires-Dist: tensorboardx
Requires-Dist: pandas
Requires-Dist: rtree
Requires-Dist: matplotlib
Requires-Dist: lark
Requires-Dist: setuptools
